LICENSE
pygasus/__init__.py
pygasus/field/__init__.py
pygasus/field/base.py
pygasus/field/helpers.py
pygasus/field/one2one.py
pygasus/model/__init__.py
pygasus/model/base.py
pygasus/model/collections/__init__.py
pygasus/model/collections/sequence.py
pygasus/model/custom_field.py
pygasus/model/decorators/__init__.py
pygasus/model/decorators/lazy_property.py
pygasus/model/helpers.py
pygasus/model/repository.py
pygasus/storage/__init__.py
pygasus/storage/abc.py
pygasus/storage/query_builder.py
pygasus/storage/sql/__init__.py
pygasus/storage/sql/engine.py
pygasus/storage/sql/query_builder.py
pygasus-0.10.4.dist-info/LICENSE
pygasus-0.10.4.dist-info/WHEEL
pygasus-0.10.4.dist-info/METADATA
pygasus-0.10.4.dist-info/RECORD
