Metadata-Version: 2.1
Name: pygasus
Version: 0.10.4
Summary: A lightweight ORM built on top of Pydantic
Home-page: https://github.com/talismud/pygasus
License: BSD-3-Clause
Keywords: ORM,Pydantic,SQL,SQLAlchemy
Author: Vincent Le Goff
Author-email: vincent.legoff.srs@gmail.com
Requires-Python: >=3.7
Classifier: Development Status :: 2 - Pre-Alpha
Classifier: Environment :: Console
Classifier: Intended Audience :: Developers
Classifier: Intended Audience :: Information Technology
Classifier: License :: OSI Approved :: BSD License
Classifier: Natural Language :: English
Classifier: Operating System :: OS Independent
Classifier: Programming Language :: Python :: 3
Classifier: Programming Language :: Python :: 3.10
Classifier: Programming Language :: Python :: 3.7
Classifier: Programming Language :: Python :: 3.8
Classifier: Programming Language :: Python :: 3.9
Classifier: Topic :: Database
Requires-Dist: SQLAlchemy (>=1.4.22,<2.0.0)
Requires-Dist: alembic (>=1.7.7,<2.0.0)
Requires-Dist: email-validator (>=1.1.3,<2.0.0)
Requires-Dist: pydantic (>=1.8.2,<2.0.0)
Requires-Dist: typing-compat (>=0.1.0,<0.2.0)
Project-URL: Documentation, https://github.com/talismud/pygasus
Project-URL: Repository, https://github.com/talismud/pygasus
